avocado_varianter_yaml_to_mux/mux.py
avocado_varianter_yaml_to_mux/varianter_yaml_to_mux.py
avocado_framework_plugin_varianter_yaml_to_mux-113.0.dist-info/METADATA
avocado_framework_plugin_varianter_yaml_to_mux-113.0.dist-info/WHEEL
avocado_framework_plugin_varianter_yaml_to_mux-113.0.dist-info/entry_points.txt
avocado_framework_plugin_varianter_yaml_to_mux-113.0.dist-info/top_level.txt
avocado_framework_plugin_varianter_yaml_to_mux-113.0.dist-info/RECORD
