Metadata-Version: 2.4
Name: avocado-framework-plugin-varianter-yaml-to-mux
Version: 113.0
Summary: Avocado Varianter plugin to parse YAML file into variants
Home-page: http://avocado-framework.github.io/
Author: Avocado Developers
Author-email: avocado-devel@redhat.com
Requires-Dist: avocado-framework==113.0
Requires-Dist: PyYAML>=4.2b2
Dynamic: author
Dynamic: author-email
Dynamic: description
Dynamic: description-content-type
Dynamic: home-page
Dynamic: requires-dist
Dynamic: summary
